{"id":875825670,"keymap":[[{"col":0,"row":0,"val":168},{"col":1,"row":0,"val":41},{"col":2,"row":0,"val":76},{"col":3,"row":0,"val":43},{"col":4,"row":0,"val":42},{"col":0,"row":1,"val":30465},{"col":1,"row":1,"val":83},{"col":2,"row":1,"val":84},{"col":3,"row":1,"val":85},{"col":4,"row":1,"val":86},{"col":0,"row":2,"val":30466},{"col":1,"row":2,"val":95},{"col":2,"row":2,"val":96},{"col":3,"row":2,"val":97},{"col":4,"row":2,"val":87},{"col":0,"row":3,"val":30467},{"col":1,"row":3,"val":92},{"col":2,"row":3,"val":93},{"col":3,"row":3,"val":94},{"col":4,"row":3,"val":0},{"col":0,"row":4,"val":30468},{"col":1,"row":4,"val":89},{"col":2,"row":4,"val":90},{"col":3,"row":4,"val":91},{"col":4,"row":4,"val":0},{"col":0,"row":5,"val":21025},{"col":1,"row":5,"val":98},{"col":2,"row":5,"val":0},{"col":3,"row":5,"val":99},{"col":4,"row":5,"val":88},{"col":0,"row":6,"val":0},{"col":1,"row":6,"val":0},{"col":2,"row":6,"val":0},{"col":3,"row":6,"val":0},{"col":4,"row":6,"val":0},{"col":0,"row":7,"val":0},{"col":1,"row":7,"val":0},{"col":2,"row":7,"val":0},{"col":3,"row":7,"val":0},{"col":4,"row":7,"val":0},{"col":0,"row":8,"val":0},{"col":1,"row":8,"val":0}],[{"col":0,"row":0,"val":30752},{"col":1,"row":0,"val":32267},{"col":2,"row":0,"val":32268},{"col":3,"row":0,"val":32269},{"col":4,"row":0,"val":32270},{"col":0,"row":1,"val":1},{"col":1,"row":1,"val":30753},{"col":2,"row":1,"val":30759},{"col":3,"row":1,"val":30755},{"col":4,"row":1,"val":1},{"col":0,"row":2,"val":1},{"col":1,"row":2,"val":30754},{"col":2,"row":2,"val":30760},{"col":3,"row":2,"val":30756},{"col":4,"row":2,"val":1},{"col":0,"row":3,"val":1},{"col":1,"row":3,"val":30757},{"col":2,"row":3,"val":30761},{"col":3,"row":3,"val":172},{"col":4,"row":3,"val":0},{"col":0,"row":4,"val":1},{"col":1,"row":4,"val":30758},{"col":2,"row":4,"val":30762},{"col":3,"row":4,"val":174},{"col":4,"row":4,"val":0},{"col":0,"row":5,"val":1},{"col":1,"row":5,"val":30752},{"col":2,"row":5,"val":0},{"col":3,"row":5,"val":171},{"col":4,"row":5,"val":1},{"col":0,"row":6,"val":0},{"col":1,"row":6,"val":0},{"col":2,"row":6,"val":0},{"col":3,"row":6,"val":0},{"col":4,"row":6,"val":0},{"col":0,"row":7,"val":0},{"col":1,"row":7,"val":0},{"col":2,"row":7,"val":0},{"col":3,"row":7,"val":0},{"col":4,"row":7,"val":0},{"col":0,"row":8,"val":0},{"col":1,"row":8,"val":0}],[{"col":0,"row":0,"val":1},{"col":1,"row":0,"val":1},{"col":2,"row":0,"val":1},{"col":3,"row":0,"val":1},{"col":4,"row":0,"val":1},{"col":0,"row":1,"val":1},{"col":1,"row":1,"val":1},{"col":2,"row":1,"val":1},{"col":3,"row":1,"val":1},{"col":4,"row":1,"val":1},{"col":0,"row":2,"val":1},{"col":1,"row":2,"val":1},{"col":2,"row":2,"val":1},{"col":3,"row":2,"val":1},{"col":4,"row":2,"val":1},{"col":0,"row":3,"val":1},{"col":1,"row":3,"val":1},{"col":2,"row":3,"val":1},{"col":3,"row":3,"val":1},{"col":4,"row":3,"val":1},{"col":0,"row":4,"val":1},{"col":1,"row":4,"val":1},{"col":2,"row":4,"val":1},{"col":3,"row":4,"val":1},{"col":4,"row":4,"val":1},{"col":0,"row":5,"val":1},{"col":1,"row":5,"val":1},{"col":2,"row":5,"val":1},{"col":3,"row":5,"val":1},{"col":4,"row":5,"val":1},{"col":0,"row":6,"val":0},{"col":1,"row":6,"val":0},{"col":2,"row":6,"val":0},{"col":3,"row":6,"val":0},{"col":4,"row":6,"val":0},{"col":0,"row":7,"val":0},{"col":1,"row":7,"val":0},{"col":2,"row":7,"val":0},{"col":3,"row":7,"val":0},{"col":4,"row":7,"val":0},{"col":0,"row":8,"val":0},{"col":1,"row":8,"val":0}],[{"col":0,"row":0,"val":1},{"col":1,"row":0,"val":1},{"col":2,"row":0,"val":1},{"col":3,"row":0,"val":1},{"col":4,"row":0,"val":1},{"col":0,"row":1,"val":1},{"col":1,"row":1,"val":1},{"col":2,"row":1,"val":1},{"col":3,"row":1,"val":1},{"col":4,"row":1,"val":1},{"col":0,"row":2,"val":1},{"col":1,"row":2,"val":1},{"col":2,"row":2,"val":1},{"col":3,"row":2,"val":1},{"col":4,"row":2,"val":1},{"col":0,"row":3,"val":1},{"col":1,"row":3,"val":1},{"col":2,"row":3,"val":1},{"col":3,"row":3,"val":1},{"col":4,"row":3,"val":1},{"col":0,"row":4,"val":1},{"col":1,"row":4,"val":1},{"col":2,"row":4,"val":1},{"col":3,"row":4,"val":1},{"col":4,"row":4,"val":1},{"col":0,"row":5,"val":1},{"col":1,"row":5,"val":1},{"col":2,"row":5,"val":1},{"col":3,"row":5,"val":1},{"col":4,"row":5,"val":1},{"col":0,"row":6,"val":0},{"col":1,"row":6,"val":0},{"col":2,"row":6,"val":0},{"col":3,"row":6,"val":0},{"col":4,"row":6,"val":0},{"col":0,"row":7,"val":0},{"col":1,"row":7,"val":0},{"col":2,"row":7,"val":0},{"col":3,"row":7,"val":0},{"col":4,"row":7,"val":0},{"col":0,"row":8,"val":0},{"col":1,"row":8,"val":0}]],"version":"1.0.0","MD5":"7d33c3fc603c120ac628c8041cf16182","knob":[{"left":"KC_VOLD","right":"KC_VOLU"},{"left":"RGB_VAD","right":"RGB_VAI"},{"left":"KC_TRNS","right":"KC_TRNS"},{"left":"KC_TRNS","right":"KC_TRNS"}]}